MANIFEST.in
README.md
__version__.txt
pyproject.toml
setup.py
degen/__init__.py
degen/bet_models.py
degen/math_tools.py
degen/odds_models.py
degen/utils.py
degen.egg-info/PKG-INFO
degen.egg-info/SOURCES.txt
degen.egg-info/dependency_links.txt
degen.egg-info/requires.txt
degen.egg-info/top_level.txt