Metadata-Version: 2.1
Name: degen
Version: 0.1.5
Summary: Programming with betting odds, made simple
Home-page: https://github.com/jzuhusky/degen
Author: Joey Zuhusky
Author-email: jzuhusky@gmail.com
Maintainer-email: jzuhusky@gmail.com
License: MIT
Keywords: odds sportsbetting betting python betting gambling
Platform: UNKNOWN
